tests/__init__.py
tests/test_data.py
tests/test_mag_order.py
tests/test_mag_unit.py
tests/test_stdsi.py
magorder-0.20.dist-info/LICENSE
magorder-0.20.dist-info/METADATA
magorder-0.20.dist-info/WHEEL
magorder-0.20.dist-info/top_level.txt
magorder-0.20.dist-info/RECORD
