Metadata-Version: 2.1
Name: magorder
Version: 0.20
Summary: Magnitude Order
Home-page: https://github.com/russoz/magorder
Author: Alexei Znamensky
Author-email: russoz@gmail.com
Maintainer: Alexei Znamensky
Maintainer-email: russoz@gmail.com
License: GPLv3
Project-URL: Bug Tracker, https://github.com/russoz/magorder/issues
Project-URL: Source Code, https://github.com/russoz/magorder
Classifier: Development Status :: 2 - Pre-Alpha
Classifier: Intended Audience :: Developers
Classifier: Intended Audience :: Information Technology
Classifier: Operating System :: OS Independent
Classifier: License :: OSI Approved :: GNU General Public License v3 (GPLv3)
Classifier: Programming Language :: Python
Classifier: Programming Language :: Python :: 3
Classifier: Programming Language :: Python :: 3.6
Classifier: Programming Language :: Python :: 3.7
Classifier: Programming Language :: Python :: 3.8
Classifier: Programming Language :: Python :: 3.9
Classifier: Programming Language :: Python :: 3.10
Classifier: Topic :: Utilities
License-File: LICENSE
